ailuropoda/__init__.py
ailuropoda/__main__.py
ailuropoda/cbor_codegen.py
ailuropoda/main.py
ailuropoda-0.2.1.dist-info/licenses/LICENSE
ailuropoda-0.2.1.dist-info/METADATA
ailuropoda-0.2.1.dist-info/WHEEL
ailuropoda-0.2.1.dist-info/entry_points.txt
ailuropoda-0.2.1.dist-info/top_level.txt
ailuropoda-0.2.1.dist-info/RECORD
